pypcl/__init__.py
pypcl/adcups.py
pypcl/adserial.py
pypcl/adsocket.py
pypcl/adusb.py
pypcl/exceptions.py
pypcl/hpcode39.py
pypcl/hppcl.py
pypcl/pypcl.py
pypcl/toolbox.py
pypcl/zpl.py
python_printer_command_line-1.0.2.dist-info/METADATA
python_printer_command_line-1.0.2.dist-info/WHEEL
python_printer_command_line-1.0.2.dist-info/top_level.txt
python_printer_command_line-1.0.2.dist-info/RECORD
