Metadata-Version: 2.2
Name: python-printer-command-line
Version: 1.0.2
Home-page: https://github.com/rrakso/PythonPcl
Author: "Dominique Meurisse"
Author-email: "info@mchobby.be"
Maintainer: "Oskar Jaskólski"
Maintainer-email: "oskarrro90@gmail.com"
Keywords: thermal printer,labels,zebra,ZPL,PCL
Classifier: Programming Language :: Python :: 3
Classifier: License :: OSI Approved :: MIT License
Classifier: Operating System :: OS Independent
Requires-Python: >=3.6
Requires-Dist: pyserial==3.5
Requires-Dist: pycups==2.0.4
Requires-Dist: pyusb==1.3.1
